var_print/__init__.py
var_print/varPrint.py
var_print/data/color_schemes.pickle
var_print-0.0.11.dist-info/licenses/LICENSE
var_print-0.0.11.dist-info/METADATA
var_print-0.0.11.dist-info/WHEEL
var_print-0.0.11.dist-info/top_level.txt
var_print-0.0.11.dist-info/RECORD
