Metadata-Version: 2.4
Name: var_print
Version: 0.0.11
Summary: Nicer printing with var_print: Colours and structure allow quick reading of the output, at the same time the name of the variable is displayed. 
Author: André Herber
Author-email: andre.herber.programming@gmail.com
Keywords: python
Classifier: Development Status :: 1 - Planning
Classifier: Intended Audience :: Developers
Classifier: Programming Language :: Python :: 3
Classifier: Operating System :: Unix
Classifier: Operating System :: MacOS :: MacOS X
Classifier: Operating System :: Microsoft :: Windows
License-File: LICENSE
Requires-Dist: executing
Requires-Dist: colorful_terminal
Requires-Dist: asttokens
Dynamic: author
Dynamic: author-email
Dynamic: classifier
Dynamic: description
Dynamic: description-content-type
Dynamic: keywords
Dynamic: license-file
Dynamic: requires-dist
Dynamic: summary
